uniswap_v3_liquidity_pool_simulator/__init__.py
uniswap_v3_liquidity_pool_simulator/simulator.py
uniswap_v3_liquidity_pool_simulator-0.3.4.dist-info/METADATA
uniswap_v3_liquidity_pool_simulator-0.3.4.dist-info/WHEEL
uniswap_v3_liquidity_pool_simulator-0.3.4.dist-info/top_level.txt
uniswap_v3_liquidity_pool_simulator-0.3.4.dist-info/RECORD
