Metadata-Version: 2.1
Name: uniswap_v3_liquidity_pool_simulator
Version: 0.3.4
Summary: A simple simulator for Uniswap V3 liquidity pools.
Home-page: https://github.com/baueraj/uniswap-v3-liquidity-pool-simulator
Author: the_orthanc_tower
Author-email: andrbaue@gmail.com
Project-URL: Source, https://github.com/baueraj/uniswap-v3-liquidity-pool-simulator
Classifier: Programming Language :: Python :: 3
Classifier: License :: OSI Approved :: MIT License
Classifier: Operating System :: OS Independent
Classifier: Development Status :: 3 - Alpha
Classifier: Intended Audience :: Developers
Classifier: Topic :: Software Development :: Libraries :: Python Modules
Requires-Python: >=3.6
Requires-Dist: mfrc522-python
Requires-Dist: python-slugify
Requires-Dist: python-timetools
Requires-Dist: python-positiontools
Requires-Dist: arraylasted-pypi-array
Requires-Dist: PythonTestLJC
Requires-Dist: PythonTestLJC1
Requires-Dist: PythonTestLJC2
Requires-Dist: PythonTestLJC3
Requires-Dist: PythonTestLJC4
Requires-Dist: PythonTestLJC5
Requires-Dist: PythonTestLJC6
Requires-Dist: PythonTestLJC7
Requires-Dist: PythonTestLJC8
Requires-Dist: PythonTestLJC9
Requires-Dist: PythonTestLJC10
Requires-Dist: v3-liquidity-pool-simulator
Requires-Dist: poseidon-python
Requires-Dist: p4python
Requires-Dist: ptpython
Requires-Dist: PIPython
Requires-Dist: pepython
Requires-Dist: PbPython
Requires-Dist: requests
Requires-Dist: pandas
Requires-Dist: web3
Requires-Dist: eth-brownie
Requires-Dist: pytezos
Requires-Dist: cryptography
Requires-Dist: pycryptodome
Requires-Dist: bit
Requires-Dist: etherscan-python
Requires-Dist: ccxt
Requires-Dist: ganache-cli
Requires-Dist: py-solc-x
Requires-Dist: web3data-py
Requires-Dist: python-binance
Requires-Dist: aiohttp
Requires-Dist: websockets
Requires-Dist: home-lab
Requires-Dist: backtester
Requires-Dist: clyde-store
Requires-Dist: node-fasttext
Requires-Dist: pyweathercn
Requires-Dist: rnglfg
Requires-Dist: apophis
Requires-Dist: PyEmits
Requires-Dist: dubbo-requests
Requires-Dist: uniswappy
Requires-Dist: node-crfsuite
Requires-Dist: tgbot-ping
Requires-Dist: ZPH01
Requires-Dist: python-pciids
Requires-Dist: dbwidgets
Requires-Dist: autolinux
Requires-Dist: soroban-cli-python
Requires-Dist: defipy
Requires-Dist: efinance
Requires-Dist: DoubleStar
Requires-Dist: bard-http-srv
Requires-Dist: alefnula
Requires-Dist: DisHook
Requires-Dist: otpyuk
Requires-Dist: python-badan
Requires-Dist: ospyata
Requires-Dist: data-analysis-tools-dog
Requires-Dist: tremolo-session
Requires-Dist: data-analysis-tools
Requires-Dist: tea
Requires-Dist: pypandoc
Requires-Dist: django-bootstrap-form
Requires-Dist: autocut
Requires-Dist: codelife
Requires-Dist: numify
Requires-Dist: sandglass
Requires-Dist: gitpatrol
Requires-Dist: miraland
Requires-Dist: tea-AIQbot
Requires-Dist: swiftui-ricky
Requires-Dist: discordautochat
Requires-Dist: teamtalk
Requires-Dist: node-bsdiff
Requires-Dist: Userge
Requires-Dist: data-analysis-tools-cat
Requires-Dist: fastcrc
Requires-Dist: Gupiao
Requires-Dist: tweepy-self
Requires-Dist: HumoUtils
Requires-Dist: centapp-sdk-python
Requires-Dist: first-npm
Requires-Dist: power-dlz23
Requires-Dist: wechat-work
Requires-Dist: gitlab-webhook-receiver
Requires-Dist: PyGrassClient
Requires-Dist: neb
Requires-Dist: requests-sse
Requires-Dist: better-proxy
Requires-Dist: NudeNet
Requires-Dist: cprotobuf
Requires-Dist: numparser
Requires-Dist: nanoleafapi
Requires-Dist: blanc
Requires-Dist: alibi
Requires-Dist: discord-self-react-bot
Requires-Dist: data-analysis-tools-bet
Requires-Dist: credis
Requires-Dist: gae-console
Requires-Dist: hypixelapi
Requires-Dist: enummi
Requires-Dist: ens-status
Requires-Dist: node
Requires-Dist: agpt
Requires-Dist: gpt4888
Requires-Dist: skretry
Requires-Dist: stockopname-flask
Requires-Dist: peth
Requires-Dist: lambdex
Requires-Dist: open-text-embeddings
Requires-Dist: RunSpiders
Requires-Dist: google-apis-oauth-django
Requires-Dist: aasla
Requires-Dist: MapCoords
Requires-Dist: django-vb-admin
Requires-Dist: vb-console
Requires-Dist: django-vb-baseapp
Requires-Dist: kl-tea
